<Entry>
	<InputCodePaths>
		<Process Name ="ExePath" Path ="C:\Users\320050491\CaseStudy1-brancth_patch1\CaseStudy1-brancth_patch1\AlertSystemClient\AlertSystemClient\bin\Debug\AlertSystemClient.exe"/>
		<Process Name ="SolutionPath" Path ="C:\Users\320050491\CaseStudy1-brancth_patch1\CaseStudy1-brancth_patch1\AlertSystemClient\AlertSystemClient.sln"/>
	</InputCodePaths>
	<Tools>
		<Tool Name ="FxCop" Path="C:\Program Files (x86)\Microsoft Fxcop 10.0\FxCopCmd.exe"/>
		<Tool Name ="NDepend" Path="C:\Users\320050491\StaticAnalysisTool\NDepend_2019.2.6.9270\NDepend.Console.exe"/>
	</Tools>
</Entry>